meshlib/MRDarkTheme.json
meshlib/MRLightTheme.json
meshlib/NotoSans-Regular.ttf
meshlib/NotoSans-SemiBold.ttf
meshlib/NotoSansMono-Regular.ttf
meshlib/NotoSansSC-Regular.otf
meshlib/__init__.py
meshlib/fa-solid-900.ttf
meshlib/libpybind11nonlimitedapi_meshlib_3.10.so
meshlib/libpybind11nonlimitedapi_meshlib_3.11.so
meshlib/libpybind11nonlimitedapi_meshlib_3.12.so
meshlib/libpybind11nonlimitedapi_meshlib_3.13.so
meshlib/libpybind11nonlimitedapi_meshlib_3.14.so
meshlib/libpybind11nonlimitedapi_meshlib_3.8.so
meshlib/libpybind11nonlimitedapi_meshlib_3.9.so
meshlib/mrcudapy.pyi
meshlib/mrcudapy.so
meshlib/mrmeshnumpy.pyi
meshlib/mrmeshnumpy.so
meshlib/mrmeshpy.pyi
meshlib/mrmeshpy.so
meshlib/mrviewerpy.pyi
meshlib/mrviewerpy.so
meshlib/resource/independent_icons/X1/Plane Import.png
meshlib/resource/independent_icons/X1/Plane XY.png
meshlib/resource/independent_icons/X1/Plane XZ.png
meshlib/resource/independent_icons/X1/Plane YZ.png
meshlib/resource/independent_icons/X1/mouse left.png
meshlib/resource/independent_icons/X1/mouse right.png
meshlib/resource/independent_icons/X1/mouse scroll.png
meshlib/resource/independent_icons/X3/Plane Import.png
meshlib/resource/independent_icons/X3/Plane XY.png
meshlib/resource/independent_icons/X3/Plane XZ.png
meshlib/resource/independent_icons/X3/Plane YZ.png
meshlib/resource/independent_icons/X3/mouse left.png
meshlib/resource/independent_icons/X3/mouse right.png
meshlib/resource/independent_icons/X3/mouse scroll.png
meshlib/resource/object_icons/X1/AngleMeasurementObject.png
meshlib/resource/object_icons/X1/CircleObject.png
meshlib/resource/object_icons/X1/ConeObject.png
meshlib/resource/object_icons/X1/CylinderObject.png
meshlib/resource/object_icons/X1/DistanceMeasurementObject.png
meshlib/resource/object_icons/X1/LineObject.png
meshlib/resource/object_icons/X1/Object.png
meshlib/resource/object_icons/X1/ObjectDistanceMap.png
meshlib/resource/object_icons/X1/ObjectGcode.png
meshlib-3.1.0.75.dist-info/METADATA
meshlib-3.1.0.75.dist-info/WHEEL
meshlib-3.1.0.75.dist-info/top_level.txt
meshlib-3.1.0.75.dist-info/RECORD
meshlib-3.1.0.75.dist-info/licenses/LICENSE
meshlib-3.1.0.75.dist-info/sboms/auditwheel.cdx.json
