Metadata-Version: 2.4
Name: meshlib
Version: 3.1.0.75
Summary: 3d processing library
Author-email: MeshLib Team <support@meshinspector.com>
License: NON-COMMERCIAL & education LICENSE AGREEMENT
Project-URL: Homepage, https://meshlib.io/
Project-URL: Documentation, https://meshlib.io/documentation/
Project-URL: Source, https://github.com/MeshInspector/MeshLib
Project-URL: Bug Reports, https://github.com/MeshInspector/MeshLib/issues
Classifier: Programming Language :: Python :: 3.8
Classifier: Programming Language :: Python :: 3.9
Classifier: Programming Language :: Python :: 3.10
Classifier: Programming Language :: Python :: 3.11
Classifier: Programming Language :: Python :: 3.12
Classifier: Programming Language :: Python :: 3.13
Classifier: Programming Language :: Python :: 3.14
Classifier: License :: Free For Educational Use
Classifier: License :: Free for non-commercial use
Classifier: Operating System :: Microsoft :: Windows
Classifier: Operating System :: POSIX :: Linux
Classifier: Operating System :: MacOS :: MacOS X
Requires-Python: >=3.8
License-File: LICENSE
Requires-Dist: numpy>=1.19.0
Dynamic: license-file
